oracle/Oracle.py
oracle/__init__.py
oracle/resolve/PredictionResolver.py
oracle/resolve/__init__.py
oracle/tools/__init__.py
oracle/tools/delta_calc.py
persuader_technology_automata_oracles-0.2.3.dist-info/LICENSE
persuader_technology_automata_oracles-0.2.3.dist-info/METADATA
persuader_technology_automata_oracles-0.2.3.dist-info/WHEEL
persuader_technology_automata_oracles-0.2.3.dist-info/top_level.txt
persuader_technology_automata_oracles-0.2.3.dist-info/RECORD
