Metadata-Version: 2.1
Name: persuader-technology-automata-oracles
Version: 0.2.3
Summary: Automata Oracles
Author: Persuader Technology
Author-email: software@persuader.technology
License: UNLICENSE
Classifier: Programming Language :: Python :: 3
License-File: LICENSE
Requires-Dist: persuader-technology-automata-core (>=0.5.7)
Requires-Dist: persuader-technology-automata-utilities (>=0.1.4)
Requires-Dist: persuader-technology-automata-exchange (>=0.1.7)
